LICENSE
README.md
pyproject.toml
src/pbit/__init__.py
src/pbit.egg-info/PKG-INFO
src/pbit.egg-info/SOURCES.txt
src/pbit.egg-info/dependency_links.txt
src/pbit.egg-info/requires.txt
src/pbit.egg-info/top_level.txt
src/pbit/datamodelschema/__init__.py
src/pbit/datamodelschema/column.py
src/pbit/datamodelschema/dax.py
src/pbit/datamodelschema/measure.py
src/pbit/datamodelschema/partition.py
src/pbit/datamodelschema/powerquery.py
src/pbit/datamodelschema/relationship.py
src/pbit/datamodelschema/table.py
src/pbit/datamodelschema/typeholder.py