Metadata-Version: 2.1
Name: pbit
Version: 0.2.2
Summary: a package with useful functions for downloading and working with midas generated analytics data
Author-email: nightcycle <coyer@nightcycle.us>
Classifier: Programming Language :: Python :: 3
Classifier: Operating System :: OS Independent
Requires-Python: >=3.10
License-File: LICENSE
